cmakerer/__init__.py
cmakerer-1.3.2.dist-info/LICENSE
cmakerer-1.3.2.dist-info/METADATA
cmakerer-1.3.2.dist-info/WHEEL
cmakerer-1.3.2.dist-info/entry_points.txt
cmakerer-1.3.2.dist-info/top_level.txt
cmakerer-1.3.2.dist-info/RECORD
