Metadata-Version: 2.1
Name: cmakerer
Version: 1.3.2
Summary: Generates CMakeLists.txt files from arbitrary C/C++ codebases.
Home-page: https://github.com/ChaosData/cmakerer
Author: Jeff Dileo
Author-email: jtdileo@gmail.com
License: BSD (2 Clause)
Keywords: cmake clion
Classifier: License :: OSI Approved :: BSD License
Classifier: Programming Language :: Python :: 3.6
Requires-Python: >=3.6.0
License-File: LICENSE
